LICENSE.txt
py_epg/__init__.py
py_epg/__main__.py
py_epg/common/__init__.py
py_epg/common/epg_scraper.py
py_epg/common/logging.py
py_epg/common/multiprocess_helper.py
py_epg/common/requests.py
py_epg/common/types.py
py_epg/common/utils.py
py_epg/logging.yaml
py_epg/main.py
py_epg/scrapers/__init__.py
py_epg/scrapers/m_musor_tv.py
py_epg-0.3.0.dist-info/entry_points.txt
py_epg-0.3.0.dist-info/LICENSE.txt
py_epg-0.3.0.dist-info/WHEEL
py_epg-0.3.0.dist-info/METADATA
py_epg-0.3.0.dist-info/RECORD
