Metadata-Version: 2.1
Name: py-epg
Version: 0.3.0
Summary: py_epg is an easy to use, modular, multi-process EPG grabber written in Python.
Home-page: https://github.com/szab100/py-epg
License: MIT
Keywords: xmltv,epg
Author: Szabolcs Fruhwald
Author-email: mail@szab100.com
Requires-Python: >=3.7,<4.0
Classifier: License :: OSI Approved :: MIT License
Classifier: Programming Language :: Python :: 3
Classifier: Programming Language :: Python :: 3.10
Classifier: Programming Language :: Python :: 3.7
Classifier: Programming Language :: Python :: 3.8
Classifier: Programming Language :: Python :: 3.9
Requires-Dist: PyYAML (>=6.0,<7.0)
Requires-Dist: beautifulsoup4 (>=4.10.0,<5.0.0)
Requires-Dist: fake-useragent (>=0.1.11,<0.2.0)
Requires-Dist: lxml (>=4.6.3,<5.0.0)
Requires-Dist: py-xmltv (>=1.0.8,<2.0.0)
Requires-Dist: python-dateutil (>=2.8.2,<3.0.0)
Requires-Dist: python-xmltv (>=1.4.3,<2.0.0)
Requires-Dist: requests (>=2.26.0,<3.0.0)
Requires-Dist: roman (>=3.3,<4.0)
Requires-Dist: tqdm (>=4.62.3,<5.0.0)
Project-URL: Repository, https://github.com/szab100/py-epg
